ChefsHatGym/__init__.py
ChefsHatGym/KEF/DataSetManager.py
ChefsHatGym/KEF/ExperimentManager.py
ChefsHatGym/KEF/LogManager.py
ChefsHatGym/KEF/MetricsManager.py
ChefsHatGym/KEF/PlotManager.py
ChefsHatGym/KEF/RenderManager.py
ChefsHatGym/KEF/StatisticsManager.py
ChefsHatGym/KEF/__init__.py
ChefsHatGym/agents/__init__.py
ChefsHatGym/agents/agent_random.py
ChefsHatGym/agents/chefs_hat_agent.py
ChefsHatGym/agents/chefs_hat_agent_socket.py
ChefsHatGym/agents/spectator_logger.py
ChefsHatGym/agents/base_classes/__init__.py
ChefsHatGym/agents/base_classes/chefs_hat_player.py
ChefsHatGym/agents/base_classes/chefs_hat_spectator.py
ChefsHatGym/env/ChefsHatEnv.py
ChefsHatGym/env/__init__.py
ChefsHatGym/gameRooms/__init__.py
ChefsHatGym/gameRooms/chefs_hat_room_local.py
ChefsHatGym/gameRooms/chefs_hat_room_remote.py
ChefsHatGym/gameRooms/chefs_hat_room_server.py
ChefsHatGym/gameRooms/chefs_hat_tournament.py
ChefsHatGym/rewards/__init__.py
ChefsHatGym/rewards/only_winning.py
ChefsHatGym/rewards/performance_score.py
ChefsHatGym/rewards/reward.py
ChefsHatGym/utils/__init__.py
ChefsHatGym/utils/utils.py
agents/__init__.py
agents/agent_dqn.py
agents/agent_ppo.py
agents/agent_ppo_old.py
agents/base_agent.py
agents/base_agent_server.py
agents/random_agent.py
rooms/__init__.py
rooms/agent_communication.py
rooms/local_communicationn.py
rooms/remote_communication.py
rooms/room.py
rooms/room_old.py
server/__init__.py
server/communication_protocol.py
chefshatgym-3.0.0.1.dist-info/LICENSE
chefshatgym-3.0.0.1.dist-info/METADATA
chefshatgym-3.0.0.1.dist-info/WHEEL
chefshatgym-3.0.0.1.dist-info/top_level.txt
chefshatgym-3.0.0.1.dist-info/RECORD
