Metadata-Version: 2.1
Name: chefshatgym
Version: 3.0.0.1
Summary: A python interface for training Reinforcement Learning agents to play the Chef's Hat Card Game.
Home-page: https://github.com/pablovin/ChefsHatGYM
Author: Pablo Barros
Author-email: Pablo Barros <pablovin@gmail.com>
License: MIT
Classifier: Development Status :: 3 - Alpha
Classifier: Intended Audience :: Developers
Classifier: Intended Audience :: Information Technology
Classifier: Intended Audience :: Science/Research
Classifier: License :: OSI Approved :: MIT License
Classifier: Programming Language :: Python
Classifier: Programming Language :: Python :: 3.6
Classifier: Programming Language :: Python :: 3.7
Classifier: Programming Language :: Python :: 3.8
Classifier: Programming Language :: Python :: 3 :: Only
Classifier: Topic :: Games/Entertainment :: Simulation
Classifier: Topic :: Games/Entertainment :: Turn Based Strategy
Classifier: Topic :: Internet
Classifier: Topic :: Scientific/Engineering :: Artificial Intelligence
Classifier: Programming Language :: Python :: Implementation :: CPython
Classifier: Programming Language :: Python :: Implementation :: PyPy
Requires-Python: >=3.10
License-File: LICENSE
Requires-Dist: matplotlib ==3.8.0
Requires-Dist: numpy ==1.26.1
Requires-Dist: pandas ==2.1.1
Requires-Dist: websockets ==15.0.1
